[
  {
    "img": "../static/portfolio_img/pf2.png",
    "name": "MovieSearch",
    "git": "https://github.com/ggj102/movieSearch",
    "web": "https://movie-search-one.vercel.app/",
    "explan": [
      "ReactJS로 구현한 페이지",
      "Route를 이용하여 페이지 전환 구현",
      "RESTful API를 이용한 통신 작업",
      "Mobx로 전역 상태 관리"
    ]
  },
  {
    "img": "../static/portfolio_img/pf3.png",
    "name": "ShoppingMall",
    "git": "https://github.com/ggj102/portfolio_shoppingmall",
    "web": "https://portfolio-shoppingmall.vercel.app/",
    "explan": [
      "ReactJS로 구현한 페이지",
      "Route를 이용하여 페이지 전환 구현",
      "RESTful API를 이용한 통신 작업",
      "유효성 검증 라이브러리 yup 적용",
      "grid를 활용한 레이아웃",
      "Redux로 전역 상태 관리"
    ]
  },
  {
    "img": "../static/portfolio_img/pf4.png",
    "name": "WeatherInfo",
    "git": "https://github.com/ggj102/weatherInfo",
    "web": "https://weather-info-theta.vercel.app/",
    "explan": [
      "ReactJS로 구현한 페이지",
      "날씨 API 연동",
      "현재 위치 검색 기능 구현",
      "카카오 맵 API를 이용해 현재 위치 좌표 -> 주소로 변환",
      "자동완성 검색 기능 구현"
    ]
  },
  {
    "img": "../static/portfolio_img/pf5.png",
    "name": "MyProfile",
    "git": "https://github.com/ggj102/myProfile",
    "web": "my-profile-rosy.vercel.app",
    "explan": [
      "NextJS로 구현한 페이지",
      "Styled-component의 특징인 props를 사용해 다크 모드, 라이트 모드 기능 구현",
      "반응형 웹 구현",
      "Redux로 전역 상태 관리",
      "portfolio 페이지 grid 적용"
    ]
  }
]
